enigma/__init__.py
enigma/builtin_rotors.py
enigma/machine.py
enigma/plug_board.py
enigma/plug_lead.py
enigma/rotor.py
enigma/version.py
enigma_emulator-1.2.1.dist-info/METADATA
enigma_emulator-1.2.1.dist-info/WHEEL
enigma_emulator-1.2.1.dist-info/top_level.txt
enigma_emulator-1.2.1.dist-info/RECORD
