Metadata-Version: 2.1
Name: enigma-emulator
Version: 1.2.1
Summary: Enigma Machine Emulator
Home-page: https://github.com/aurbano/enigma_py
Author: Alejandro U. Alvarez
Author-email: aluralma@gmail.com
License: MIT
Platform: UNKNOWN
Classifier: Development Status :: 5 - Production/Stable
Classifier: Intended Audience :: Science/Research
Classifier: Programming Language :: Python :: 3.6
